ezmongo/__init__.a
ezmongo/__init__.py
ezmongo-0.1.0.dist-info/METADATA
ezmongo-0.1.0.dist-info/WHEEL
ezmongo-0.1.0.dist-info/RECORD
