Metadata-Version: 2.1
Name: ezmongo
Version: 0.1.0
Summary: Easy mongo db with typed objects
Author: Izak57
Author-email: izak57k@gmail.com
Requires-Python: >=3.12,<4.0
Classifier: Programming Language :: Python :: 3
Classifier: Programming Language :: Python :: 3.12
Requires-Dist: pydantic (>=2.8.2,<3.0.0)
Requires-Dist: pymongo (>=4.8.0,<5.0.0)
